pelican/plugins/pelican_events/.pylintrc
pelican/plugins/pelican_events/__init__.py
pelican/plugins/pelican_events/pelican_events.py
pelican/plugins/pelican_events/tests/t500/README.md
pelican/plugins/pelican_events/tests/t500/test_run/001/content/2025-09-18-meetup.md
pelican/plugins/pelican_events/tests/t500/test_run/001/expected_calendar.ics
pelican/plugins/pelican_events/tests/t500/test_run/001/pelicanconf.py
pelican/plugins/pelican_events/tests/t500/test_run/001/publishconf.py
pelican/plugins/pelican_events/tests/t500/test_run/002/expected_calendar.ics
pelican/plugins/pelican_events/tests/t500/test_run/002/pelicanconf.py
pelican/plugins/pelican_events/tests/t500/test_run/002/publishconf.py
pelican/plugins/pelican_events/tests/test_010_util_funcs.py
pelican/plugins/pelican_events/tests/test_011_timestamp.py
pelican/plugins/pelican_events/tests/test_020_mid_funcs.py
pelican/plugins/pelican_events/tests/test_200_recurrence.py
pelican/plugins/pelican_events/tests/test_300_ical.py
pelican/plugins/pelican_events/tests/test_500_integ.py
pelican/plugins/pelican_events/version.py
pelican_events-0.1.4.dist-info/METADATA
pelican_events-0.1.4.dist-info/WHEEL
pelican_events-0.1.4.dist-info/entry_points.txt
pelican_events-0.1.4.dist-info/licenses/LICENSE
pelican_events-0.1.4.dist-info/RECORD
