Metadata-Version: 2.1
Name: pelican-events
Version: 0.1.4
Summary: iCalendar events plugin for Pelican
Keywords: pelican,plugin,icalendar,events
Author-Email: Ian Kluft <ko6yq.dev+python@gmail.com>
License: AGPL-3.0
Classifier: Development Status :: 3 - Alpha
Classifier: Environment :: Console
Classifier: Framework :: Pelican
Classifier: Framework :: Pelican :: Plugins
Classifier: Intended Audience :: End Users/Desktop
Classifier: License :: OSI Approved :: GNU Affero General Public License v3
Classifier: Operating System :: OS Independent
Classifier: Programming Language :: Python :: 3
Classifier: Programming Language :: Python :: 3.11
Classifier: Programming Language :: Python :: 3.12
Classifier: Programming Language :: Python :: 3.13
Classifier: Programming Language :: Python :: 3.14
Classifier: Topic :: Internet :: WWW/HTTP
Classifier: Topic :: Software Development :: Libraries :: Python Modules
Project-URL: Homepage, https://github.com/ikluft/pelican-events
Project-URL: Issue Tracker, https://github.com/ikluft/pelican-events/issues
Project-URL: Changelog, https://github.com/ikluft/pelican-events/blob/main/CHANGELOG.md
Requires-Python: >=3.11
Requires-Dist: pelican>=4.5
Requires-Dist: icalendar>=6.1
Requires-Dist: recurrent>=0.4
Requires-Dist: html2text>=2025.4.15
Provides-Extra: markdown
Requires-Dist: markdown>=3.4; extra == "markdown"
